dekad/__init__.py
dekad/dekad.py
dekad/utils.py
dekad-1.1.1.dist-info/METADATA
dekad-1.1.1.dist-info/WHEEL
dekad-1.1.1.dist-info/licenses/LICENSE
dekad-1.1.1.dist-info/RECORD
