Metadata-Version: 2.4
Name: dekad
Version: 1.1.1
Summary: A Python package
Project-URL: Homepage, https://github.com/amano-takahisa/dekad
Project-URL: Repository, https://github.com/amano-takahisa/dekad
Author-email: Taka <amano.takahisa@gmail.com>
Maintainer-email: Taka <amano.takahisa@gmail.com>
License: HIPPOCRATIC LICENSE
License-File: LICENSE
Keywords: date
Classifier: Development Status :: 3 - Alpha
Classifier: Intended Audience :: Developers
Classifier: Programming Language :: Python :: 3
Classifier: Programming Language :: Python :: 3.9
Classifier: Programming Language :: Python :: 3.10
Classifier: Programming Language :: Python :: 3.11
Classifier: Programming Language :: Python :: 3.12
Classifier: Programming Language :: Python :: 3.13
Classifier: Programming Language :: Python :: 3.14
Requires-Python: >=3.9
